{"version":2,"kind":"Notebook","sha256":"a62bda2f6ca515ef502049da7be8114dccee90b38dd549a70d5f2aa8c2f1f436","slug":"index","location":"/notebooks/Intro.ipynb","dependencies":[],"frontmatter":{"title":"Intro","content_includes_title":false,"kernelspec":{"name":"kotlin","display_name":"Kotlin","language":"kotlin"},"github":"https://github.com/simongarisch/KTS","keywords":["kotlin","notebooks","jupyter","jupyter-book"],"edit_url":"https://github.com/simongarisch/KTS/blob/main/notebooks/Intro.ipynb","exports":[{"format":"ipynb","filename":"Intro.ipynb","url":"/build/Intro-83b90ddfdd45db61b8a621b057a895ef.ipynb"}]},"widgets":{},"mdast":{"type":"root","children":[{"type":"block","kind":"notebook-content","children":[{"type":"paragraph","position":{"start":{"line":3,"column":1},"end":{"line":3,"column":1}},"children":[{"type":"text","value":"Kotlin is a modern, statically typed programming language developed by JetBrains (the creators of IntelliJ IDEA) and runs on the Java Virtual Machine (JVM).","position":{"start":{"line":3,"column":1},"end":{"line":3,"column":1}},"key":"rBLXp0KDlc"}],"key":"jVJ7BcnDbk"}],"key":"KW3SzV1VY6"},{"type":"block","kind":"notebook-code","children":[{"type":"code","lang":"kotlin","executable":true,"value":"println(\"hello, world\")","key":"sMi9wizxz6"},{"type":"output","id":"ZePAOr_9PEVrW5BCO77_T","data":[{"name":"stdout","output_type":"stream","text":"hello, world\n"}],"key":"LYsboFkO4Z"}],"key":"j6YigYtlTI"},{"type":"block","kind":"notebook-code","children":[{"type":"code","lang":"kotlin","executable":true,"value":"var meaningOfLife = 42\nprintln(meaningOfLife)","key":"FvynzWdbqo"},{"type":"output","id":"lnFpEPTdmHbc288oZC_Ig","data":[{"name":"stdout","output_type":"stream","text":"42\n"}],"key":"ksPLlm3bAy"}],"key":"Irccmd2fNK"},{"type":"block","kind":"notebook-code","children":[{"type":"code","lang":"kotlin","executable":true,"value":"fun main(args: Array<String>) {\n    if (args.size > 0) {\n        println(args)\n    }\n    println(\"hello, world\")\n}\n\nval args = emptyArray<String>()\nmain(args)","key":"vCK6Y9fB4n"},{"type":"output","id":"9w-tynZsZiIkmOqjq7tnn","data":[{"name":"stdout","output_type":"stream","text":"hello, world\n"}],"key":"OxcsfOAiss"}],"key":"DZoCPzvmh1"},{"type":"block","kind":"notebook-content","children":[{"type":"paragraph","position":{"start":{"line":1,"column":1},"end":{"line":1,"column":1}},"children":[{"type":"text","value":"... all fairly straightforward ...","position":{"start":{"line":1,"column":1},"end":{"line":1,"column":1}},"key":"sqz310DszH"}],"key":"eH6ComsSoz"}],"key":"dkG5GPZYH6"},{"type":"block","kind":"notebook-content","children":[{"type":"heading","depth":2,"position":{"start":{"line":1,"column":1},"end":{"line":1,"column":1}},"children":[{"type":"text","value":"FizzBuzz","position":{"start":{"line":1,"column":1},"end":{"line":1,"column":1}},"key":"g3PyT9Qq8r"}],"identifier":"fizzbuzz","label":"FizzBuzz","html_id":"fizzbuzz","implicit":true,"key":"X2vpA2M3lo"}],"key":"zY04JM0H60"},{"type":"block","kind":"notebook-code","children":[{"type":"code","lang":"kotlin","executable":true,"value":"fun Int.isDiv(vararg ints: Int): Boolean {\n    for (i in ints) {\n        if (this % i != 0) {\n            return false\n        }\n    }\n    return true\n}","key":"ehhNmjklnx"},{"type":"output","id":"ZQgjJIaVVc-8Chti3mTqb","data":[],"key":"euWamiwv3D"}],"key":"nRsl1aqwgZ"},{"type":"block","kind":"notebook-code","children":[{"type":"code","lang":"kotlin","executable":true,"value":"3.isDiv(2)","key":"CWxpP3t0Io"},{"type":"output","id":"ggxr0YbYxeW4SA6pJ7jRh","data":[{"output_type":"execute_result","execution_count":18,"metadata":{},"data":{"text/plain":{"content":"false","content_type":"text/plain"}}}],"key":"eaq346nkXq"}],"key":"IB3w8P6xiV"},{"type":"block","kind":"notebook-code","children":[{"type":"code","lang":"kotlin","executable":true,"value":"6.isDiv(2)","key":"gu7F0ONizH"},{"type":"output","id":"hq7Ll6yehQelhEuqvJXKV","data":[{"output_type":"execute_result","execution_count":19,"metadata":{},"data":{"text/plain":{"content":"true","content_type":"text/plain"}}}],"key":"jswbg7o5jK"}],"key":"hkBVqLlaGD"},{"type":"block","kind":"notebook-code","children":[{"type":"code","lang":"kotlin","executable":true,"value":"fun fizzBuzz(n: Int): String {\n    if (n.isDiv(3, 5)) {\n        return \"FizzBuzz\"\n    } else if (n.isDiv(3)) {\n        return \"Fizz\"\n    } else if (n.isDiv(5)) {\n        return \"Buzz\"\n    }\n\n    return n.toString()\n}","key":"I0nqtpTMYJ"},{"type":"output","id":"Mjqz_hFz7XcOuKoQvn-Om","data":[],"key":"xeaOZMrFay"}],"key":"xJDnyNDOhn"},{"type":"block","kind":"notebook-code","children":[{"type":"code","lang":"kotlin","executable":true,"value":"for (n in 1..20) {\n    println(fizzBuzz(n))\n}","key":"BrAJbOaH9j"},{"type":"output","id":"gEhMl2dmuT8-VlRXnB3p6","data":[{"name":"stdout","output_type":"stream","text":"1\n2\nFizz\n4\nBuzz\nFizz\n7\n8\nFizz\nBuzz\n11\nFizz\n13\n14\nFizzBuzz\n16\n17\nFizz\n19\nBuzz\n"}],"key":"SDbWo2PBsB"}],"key":"hsq1lrGHf5"},{"type":"block","kind":"notebook-content","children":[{"type":"paragraph","position":{"start":{"line":1,"column":1},"end":{"line":1,"column":1}},"children":[{"type":"text","value":"Alternatively...","position":{"start":{"line":1,"column":1},"end":{"line":1,"column":1}},"key":"EWEEp3ho1n"}],"key":"xXcu2sG93t"},{"type":"paragraph","position":{"start":{"line":3,"column":1},"end":{"line":3,"column":1}},"children":[{"type":"text","value":"The when expression serves as an expressive alternative to the switch.","position":{"start":{"line":3,"column":1},"end":{"line":3,"column":1}},"key":"eVghsY3ep4"}],"key":"KF8TZ45KXK"}],"key":"weknB8zZiN"},{"type":"block","kind":"notebook-code","children":[{"type":"code","lang":"kotlin","executable":true,"value":"fun fizzBuzz2(n: Int): String {\n    when {\n        n.isDiv(3, 5) -> return \"FizzBuzz\"\n        n.isDiv(3) -> return \"Fizz\"\n        n.isDiv(5) -> return \"Buzz\"\n        else -> return n.toString()\n    }\n}","key":"VO3AgoTr7P"},{"type":"output","id":"ioolm0ku3ZU-FTteNX-g6","data":[],"key":"cHb4DxGFWr"}],"key":"C2pg4Q6m0b"},{"type":"block","kind":"notebook-code","children":[{"type":"code","lang":"kotlin","executable":true,"value":"for (n in 1..20) {\n    println(fizzBuzz2(n))\n}","key":"m5mT3s2RMx"},{"type":"output","id":"JAnSa6kn73K5K3Wc6ICV4","data":[{"name":"stdout","output_type":"stream","text":"1\n2\nFizz\n4\nBuzz\nFizz\n7\n8\nFizz\nBuzz\n11\nFizz\n13\n14\nFizzBuzz\n16\n17\nFizz\n19\nBuzz\n"}],"key":"BFxSmuFIMx"}],"key":"ruRcPvQwH7"},{"type":"block","kind":"notebook-content","children":[{"type":"thematicBreak","position":{"start":{"line":1,"column":1},"end":{"line":1,"column":1}},"key":"lcmK0KDOjN"}],"key":"EtzVieLZ03"}],"key":"PyJ2PgZqGw"},"references":{"cite":{"order":[],"data":{}}},"footer":{"navigation":{}},"domain":"http://localhost:3001"}